odoo9_addon_website_img_bg_style-9.0.1.0.0-py2.7-nspkg.pth
odoo9_addon_website_img_bg_style-9.0.1.0.0.dist-info/top_level.txt
odoo9_addon_website_img_bg_style-9.0.1.0.0.dist-info/WHEEL
odoo9_addon_website_img_bg_style-9.0.1.0.0.dist-info/RECORD
odoo9_addon_website_img_bg_style-9.0.1.0.0.dist-info/metadata.json
odoo9_addon_website_img_bg_style-9.0.1.0.0.dist-info/DESCRIPTION.rst
odoo9_addon_website_img_bg_style-9.0.1.0.0.dist-info/METADATA
odoo9_addon_website_img_bg_style-9.0.1.0.0.dist-info/namespace_packages.txt
odoo_addons/website_img_bg_style/__openerp__.py
odoo_addons/website_img_bg_style/__init__.py
odoo_addons/website_img_bg_style/README.rst
odoo_addons/website_img_bg_style/i18n/it.po
odoo_addons/website_img_bg_style/i18n/es.po
odoo_addons/website_img_bg_style/i18n/sl.po
odoo_addons/website_img_bg_style/i18n/fr.po
odoo_addons/website_img_bg_style/views/snippets.xml
odoo_addons/website_img_bg_style/views/assets.xml
odoo_addons/website_img_bg_style/static/description/icon.png
odoo_addons/website_img_bg_style/static/src/css/styles.sass
